{
    "link": "https:\/\/terraria.gamepedia.com\/Ancient_Headdress",
    "title": "Ancient set",
    "info": "The <b>Ancient set<\/b> is a Hardmode vanity set which consists of the <b>Ancient Headdress<\/b>, <b>Ancient Garments<\/b> and <b>Ancient Slacks<\/b>.\n",
    "stat": "<table class=\"stat\"><tbody><tr><th>Type<\/th><td><div class=\"tags\"><span class=\"nowrap tag\">Vanity<\/span><span class=\"nowrap tag\">Set<\/span><\/div><\/td><\/tr><tr><th>Rarity<\/th><td><span class=\"rarity\"><s style=\"display:none;\">03*<\/s><img src=\".\/data\/images\/rarity level: 3.png\" alt=\"rarity level: 3\" title=\"rarity level: 3\" \/><\/span><\/td><\/tr><tr><th>Sell<\/th><td><span class=\"coin\" title=\"1 Gold 50 Silver Coins\" data-sort-value=\"15000\"><span class=\"gc\">1<\/span><span class=\"sc\">50<\/span><\/span><span class=\"note-text\"> (set)<\/span><\/td><\/tr><\/tbody><\/table>",
    "craft": [
        {
            "title": "Recipes",
            "info": "",
            "table": "<div class=\"crafts\"><div class=\"wrap\"><table class=\"sortable\" cellpadding=\"0\" cellspacing=\"0\"><tbody><tr><th class=\"result\">Result<\/th><th class=\"ingredients\">Ingredients<\/th><th class=\"station\">Crafting station<\/th><\/tr><tr data-rowid=\"1\"><td class=\"result\" rowspan=\"1\"><span class=\"i multi-line\"><img src=\".\/data\/images\/ancient garments.png\" alt=\"ancient garments\" title=\"ancient garments\" \/><span><span title=\"Ancient Garments\">Ancient Garments<\/span><span class=\"eico\"><img src=\".\/data\/images\/desktop, console, and mobile versions.png\" alt=\"desktop, console, and mobile versions\" title=\"desktop, console, and mobile versions\" \/><\/span><\/span><\/span><\/td><td class=\"ingredients\"><ul><li><span class=\"i\"><img src=\".\/data\/images\/silk.png\" alt=\"silk\" title=\"silk\" \/><span><span>Silk<\/span><\/span><\/span> <span class=\"note-text\">(15)<\/span><\/li><li><span class=\"i\"><img src=\".\/data\/images\/ancient cloth.png\" alt=\"ancient cloth\" title=\"ancient cloth\" \/><span><span>Ancient Cloth<\/span><span class=\"eico\"><img src=\".\/data\/images\/desktop, console, and mobile versions.png\" alt=\"desktop, console, and mobile versions\" title=\"desktop, console, and mobile versions\" \/><\/span><\/span><\/span> <span class=\"note-text\">(5)<\/span><\/li><\/ul><\/td><td class=\"station\" rowspan=\"3\"><span class=\"i\"><img src=\".\/data\/images\/loom.png\" alt=\"loom\" title=\"loom\" \/><span><span>Loom<\/span><\/span><\/span><\/td><\/tr><tr data-rowid=\"2\"><td class=\"result\" rowspan=\"1\"><span class=\"i multi-line\"><img src=\".\/data\/images\/ancient headdress.png\" alt=\"ancient headdress\" title=\"ancient headdress\" \/><span><span title=\"Ancient Headdress\">Ancient Headdress<\/span><span class=\"eico\"><img src=\".\/data\/images\/desktop, console, and mobile versions.png\" alt=\"desktop, console, and mobile versions\" title=\"desktop, console, and mobile versions\" \/><\/span><\/span><\/span><\/td><td class=\"ingredients\"><ul><li><span class=\"i\"><img src=\".\/data\/images\/silk.png\" alt=\"silk\" title=\"silk\" \/><span><span>Silk<\/span><\/span><\/span> <span class=\"note-text\">(15)<\/span><\/li><li><span class=\"i\"><img src=\".\/data\/images\/ancient cloth.png\" alt=\"ancient cloth\" title=\"ancient cloth\" \/><span><span>Ancient Cloth<\/span><span class=\"eico\"><img src=\".\/data\/images\/desktop, console, and mobile versions.png\" alt=\"desktop, console, and mobile versions\" title=\"desktop, console, and mobile versions\" \/><\/span><\/span><\/span> <span class=\"note-text\">(5)<\/span><\/li><\/ul><\/td><\/tr><tr data-rowid=\"3\"><td class=\"result\" rowspan=\"1\"><span class=\"i multi-line\"><img src=\".\/data\/images\/ancient slacks.png\" alt=\"ancient slacks\" title=\"ancient slacks\" \/><span><span title=\"Ancient Slacks\">Ancient Slacks<\/span><span class=\"eico\"><img src=\".\/data\/images\/desktop, console, and mobile versions.png\" alt=\"desktop, console, and mobile versions\" title=\"desktop, console, and mobile versions\" \/><\/span><\/span><\/span><\/td><td class=\"ingredients\"><ul><li><span class=\"i\"><img src=\".\/data\/images\/silk.png\" alt=\"silk\" title=\"silk\" \/><span><span>Silk<\/span><\/span><\/span> <span class=\"note-text\">(15)<\/span><\/li><li><span class=\"i\"><img src=\".\/data\/images\/ancient cloth.png\" alt=\"ancient cloth\" title=\"ancient cloth\" \/><span><span>Ancient Cloth<\/span><span class=\"eico\"><img src=\".\/data\/images\/desktop, console, and mobile versions.png\" alt=\"desktop, console, and mobile versions\" title=\"desktop, console, and mobile versions\" \/><\/span><\/span><\/span> <span class=\"note-text\">(5)<\/span><\/li><\/ul><\/td><\/tr><\/tbody><\/table><div style=\"display: none\">total: 3 row(s)<\/div><\/div><\/div>"
        }
    ]
}