{
    "link": "https:\/\/terraria.gamepedia.com\/Corrupt_Grass_Wall",
    "title": "Corrupt Grass Wall",
    "info": "<b>Corrupt Grass Wall<\/b> is a type of Wall. Like the Grass of The Corruption, it is a dark hue of purple. On the <img src=\".\/data\/images\/desktop version.png\" alt=\"desktop version\" title=\"desktop version\" \/>\u00a0Desktop version and <img src=\".\/data\/images\/mobile version.png\" alt=\"mobile version\" title=\"mobile version\" \/>\u00a0Mobile version, it is sold by the Dryad during a Blood Moon. In all other versions, it can be destroyed, but not harvested, making it unobtainable as an item.\n",
    "stat": {
        "image": "<div class=\"section images\"><ul class=\"infobox-inline\"><li><img src=\".\/data\/images\/corrupt grass wall.png\" alt=\"corrupt grass wall\" title=\"corrupt grass wall\" \/><\/li><li><img src=\".\/data\/images\/corrupt grass wall placed.png\" alt=\"corrupt grass wall placed\" title=\"corrupt grass wall placed\" \/><\/li><\/ul><div class=\"auto\"><img src=\".\/data\/images\/auto-use.png\" alt=\"auto-use\" title=\"auto-use\" \/><\/div><div class=\"stack\" title=\"Max stack: 999\"><span style=\"cursor:pointer\"><img src=\".\/data\/images\/stack digit 9.png\" alt=\"stack digit 9\" title=\"stack digit 9\" \/><img src=\".\/data\/images\/stack digit 9.png\" alt=\"stack digit 9\" title=\"stack digit 9\" \/><img src=\".\/data\/images\/stack digit 9.png\" alt=\"stack digit 9\" title=\"stack digit 9\" \/><\/span><\/div><\/div>",
        "table": "<table class=\"stat\"><tbody><tr><th>Placeable<\/th><td><img src=\".\/data\/images\/yes.png\" alt=\"yes\" title=\"yes\" \/> <\/td><\/tr><tr><th>Use time<\/th><td>15 <span class=\"usetime\">(Very fast)<\/span><\/td><\/tr><tr><th>Rarity<\/th><td><span class=\"rarity\"><s style=\"display:none;\">00*<\/s><img src=\".\/data\/images\/rarity level: 0.png\" alt=\"rarity level: 0\" title=\"rarity level: 0\" \/><\/span><\/td><\/tr><tr><th>Sell<\/th><td><span class=\"coin\" title=\"50 Copper Coins\" data-sort-value=\"50\"><span class=\"cc\">50<\/span><\/span><\/td><\/tr><tr><th>Research<\/th><td><abbr style=\"color:#C70A7D;font-weight:bold;\" title=\"Journey Mode\">400 required<\/abbr><\/td><\/tr><\/tbody><\/table>"
    },
    "craft": []
}