{
    "link": "https:\/\/terraria.gamepedia.com\/Gel",
    "title": "Gel",
    "info": "<b>Gel<\/b> is a common crafting material dropped by most slimes and Slimed Zombies. Gel is vital due to it being an ingredient in Torches, and is used regularly from the beginning stages all the way through to endgame scenarios. It is also used as ammunition for the Flamethrower and the Elf Melter, and can therefore be stored in the player's inventory ammo slots.\n",
    "stat": {
        "image": "<div class=\"section images\"><ul class=\"infobox-inline\"><li><img src=\".\/data\/images\/gel.png\" alt=\"gel\" title=\"gel\" \/><\/li><\/ul><div class=\"stack\" title=\"Max stack: 999\"><span style=\"cursor:pointer\"><img src=\".\/data\/images\/stack digit 9.png\" alt=\"stack digit 9\" title=\"stack digit 9\" \/><img src=\".\/data\/images\/stack digit 9.png\" alt=\"stack digit 9\" title=\"stack digit 9\" \/><img src=\".\/data\/images\/stack digit 9.png\" alt=\"stack digit 9\" title=\"stack digit 9\" \/><\/span><\/div><\/div>",
        "table": "<table class=\"stat\"><tbody><tr><th>Type<\/th><td><div class=\"tags\"><span class=\"nowrap tag\">Ammunition<\/span><span class=\"nowrap tag\">Crafting material<\/span><\/div><\/td><\/tr><tr><th>Tooltip<\/th><td><i>'Both tasty and flammable'<\/i><\/td><\/tr><tr><th>Rarity<\/th><td><span class=\"rarity\"><s style=\"display:none;\">00*<\/s><img src=\".\/data\/images\/rarity level: 0.png\" alt=\"rarity level: 0\" title=\"rarity level: 0\" \/><\/span><\/td><\/tr><tr><th>Sell<\/th><td><span class=\"coin\" title=\"1 Copper Coin\" data-sort-value=\"1\"><span class=\"cc\">1<\/span><\/span><\/td><\/tr><tr><th>Research<\/th><td><abbr style=\"color:#C70A7D;font-weight:bold;\" title=\"Journey Mode\">99 required<\/abbr><\/td><\/tr><\/tbody><\/table>"
    },
    "craft": [
        {
            "title": "Used in",
            "info": "",
            "table": "<div class=\"crafts\"><div class=\"wrap\"><table class=\"sortable\" cellpadding=\"0\" cellspacing=\"0\"><tbody><tr><th class=\"result\">Result<\/th><th class=\"ingredients\">Ingredients<\/th><th class=\"station\">Crafting station<\/th><\/tr><tr data-rowid=\"1\"><td class=\"result\" rowspan=\"1\"><span class=\"i multi-line\"><img src=\".\/data\/images\/asphalt block.png\" alt=\"asphalt block\" title=\"asphalt block\" \/><span><span>Asphalt Block<\/span><\/span><\/span><\/td><td class=\"ingredients\"><ul><li><span class=\"i\"><img src=\".\/data\/images\/stone block.png\" alt=\"stone block\" title=\"stone block\" \/><span><span>Stone Block<\/span><\/span><\/span> <span class=\"note-text\">(2)<\/span><\/li><li><span class=\"i\"><img src=\".\/data\/images\/gel.png\" alt=\"gel\" title=\"gel\" \/><span><span>Gel<\/span><\/span><\/span><\/li><\/ul><\/td><td class=\"station\" rowspan=\"1\"><span class=\"i\"><img src=\".\/data\/images\/blend-o-matic.png\" alt=\"blend-o-matic\" title=\"blend-o-matic\" \/><span><span>Blend-O-Matic<\/span><\/span><\/span><\/td><\/tr><tr data-rowid=\"2\"><td class=\"result\" rowspan=\"1\"><span class=\"i multi-line\"><img src=\".\/data\/images\/sticky bomb.png\" alt=\"sticky bomb\" title=\"sticky bomb\" \/><span><span>Sticky Bomb<\/span><\/span><\/span><\/td><td class=\"ingredients\"><ul><li><span class=\"i\"><img src=\".\/data\/images\/bomb.png\" alt=\"bomb\" title=\"bomb\" \/><span><span>Bomb<\/span><\/span><\/span><\/li><li><span class=\"i\"><img src=\".\/data\/images\/gel.png\" alt=\"gel\" title=\"gel\" \/><span><span>Gel<\/span><\/span><\/span><\/li><\/ul><\/td><td class=\"station\" rowspan=\"6\">By Hand<\/td><\/tr><tr data-rowid=\"3\"><td class=\"result\" rowspan=\"1\"><span class=\"i multi-line\"><img src=\".\/data\/images\/sticky dirt bomb.png\" alt=\"sticky dirt bomb\" title=\"sticky dirt bomb\" \/><span><span>Sticky Dirt Bomb<\/span><span class=\"eico\"><img src=\".\/data\/images\/desktop and mobile versions.png\" alt=\"desktop and mobile versions\" title=\"desktop and mobile versions\" \/><\/span><\/span><\/span><\/td><td class=\"ingredients\"><ul><li><span class=\"i\"><img src=\".\/data\/images\/dirt bomb.png\" alt=\"dirt bomb\" title=\"dirt bomb\" \/><span><span>Dirt Bomb<\/span><span class=\"eico\"><img src=\".\/data\/images\/desktop and mobile versions.png\" alt=\"desktop and mobile versions\" title=\"desktop and mobile versions\" \/><\/span><\/span><\/span><\/li><li><span class=\"i\"><img src=\".\/data\/images\/gel.png\" alt=\"gel\" title=\"gel\" \/><span><span>Gel<\/span><\/span><\/span><\/li><\/ul><\/td><\/tr><tr data-rowid=\"4\"><td class=\"result\" rowspan=\"1\"><span class=\"i multi-line\"><img src=\".\/data\/images\/sticky dynamite.png\" alt=\"sticky dynamite\" title=\"sticky dynamite\" \/><span><span>Sticky Dynamite<\/span><span class=\"eico\"><img src=\".\/data\/images\/desktop, console, and mobile versions.png\" alt=\"desktop, console, and mobile versions\" title=\"desktop, console, and mobile versions\" \/><\/span><\/span><\/span><\/td><td class=\"ingredients\"><ul><li><span class=\"i\"><img src=\".\/data\/images\/dynamite.png\" alt=\"dynamite\" title=\"dynamite\" \/><span><span>Dynamite<\/span><\/span><\/span><\/li><li><span class=\"i\"><img src=\".\/data\/images\/gel.png\" alt=\"gel\" title=\"gel\" \/><span><span>Gel<\/span><\/span><\/span><\/li><\/ul><\/td><\/tr><tr data-rowid=\"5\"><td class=\"result\" rowspan=\"1\"><span class=\"i multi-line\"><img src=\".\/data\/images\/sticky glowstick.png\" alt=\"sticky glowstick\" title=\"sticky glowstick\" \/><span><span>Sticky Glowstick<\/span><\/span><\/span> <span class=\"note-text\">(5)<\/span><\/td><td class=\"ingredients\"><ul><li><span class=\"i\"><img src=\".\/data\/images\/glowstick.png\" alt=\"glowstick\" title=\"glowstick\" \/><span><span>Glowstick<\/span><\/span><\/span> <span class=\"note-text\">(5)<\/span><\/li><li><span class=\"i\"><img src=\".\/data\/images\/gel.png\" alt=\"gel\" title=\"gel\" \/><span><span>Gel<\/span><\/span><\/span><\/li><\/ul><\/td><\/tr><tr data-rowid=\"6\"><td class=\"result\" rowspan=\"1\"><span class=\"i multi-line\"><img src=\".\/data\/images\/sticky grenade.png\" alt=\"sticky grenade\" title=\"sticky grenade\" \/><span><span>Sticky Grenade<\/span><span class=\"eico\"><img src=\".\/data\/images\/desktop, console, old-gen console, and mobile versions.png\" alt=\"desktop, console, old-gen console, and mobile versions\" title=\"desktop, console, old-gen console, and mobile versions\" \/><\/span><\/span><\/span> <span class=\"note-text\">(5)<\/span><\/td><td class=\"ingredients\"><ul><li><span class=\"i\"><img src=\".\/data\/images\/grenade.png\" alt=\"grenade\" title=\"grenade\" \/><span><span>Grenade<\/span><\/span><\/span> <span class=\"note-text\">(5)<\/span><\/li><li><span class=\"i\"><img src=\".\/data\/images\/gel.png\" alt=\"gel\" title=\"gel\" \/><span><span>Gel<\/span><\/span><\/span><\/li><\/ul><\/td><\/tr><tr data-rowid=\"7\"><td class=\"result\" rowspan=\"1\"><span class=\"i multi-line\"><img src=\".\/data\/images\/torch.png\" alt=\"torch\" title=\"torch\" \/><span><span>Torch<\/span><\/span><\/span> <span class=\"note-text\">(3)<\/span><\/td><td class=\"ingredients\"><ul><li><span class=\"i\"><img src=\".\/data\/images\/gel.png\" alt=\"gel\" title=\"gel\" \/><span><span>Gel<\/span><\/span><\/span><\/li><li><span class=\"i\"><img src=\".\/data\/images\/any wood.png\" alt=\"any wood\" title=\"any wood\" \/><span><span>Any Wood<\/span><\/span><\/span><\/li><\/ul><\/td><\/tr><tr data-rowid=\"8\"><td class=\"result\" rowspan=\"2\"><span class=\"i multi-line\"><img src=\".\/data\/images\/slime crown.png\" alt=\"slime crown\" title=\"slime crown\" \/><span><span>Slime Crown<\/span><\/span><\/span> (<img src=\".\/data\/images\/desktop version.png\" alt=\"desktop version\" title=\"desktop version\" \/>\u2009<img src=\".\/data\/images\/console version.png\" alt=\"console version\" title=\"console version\" \/>\u2009<img src=\".\/data\/images\/mobile version.png\" alt=\"mobile version\" title=\"mobile version\" \/>)<\/td><td class=\"ingredients\"><ul><li><span class=\"i\"><img src=\".\/data\/images\/gel.png\" alt=\"gel\" title=\"gel\" \/><span><span>Gel<\/span><\/span><\/span> <span class=\"note-text\">(20)<\/span><\/li><li><span class=\"i\"><img src=\".\/data\/images\/gold crown.png\" alt=\"gold crown\" title=\"gold crown\" \/><span><span>Gold Crown<\/span><\/span><\/span><\/li><\/ul><\/td><td class=\"station\" rowspan=\"4\"><span class=\"i\"><img src=\".\/data\/images\/demon altar.png\" alt=\"demon altar\" title=\"demon altar\" \/><span><span>Demon Altar<\/span><\/span><\/span><br><i><b>or<\/b><\/i><br><span class=\"i\"><img src=\".\/data\/images\/crimson altar.png\" alt=\"crimson altar\" title=\"crimson altar\" \/><span><span>Crimson Altar<\/span><\/span><\/span><\/td><\/tr><tr data-rowid=\"9\"><td class=\"ingredients\"><ul><li><span class=\"i\"><img src=\".\/data\/images\/gel.png\" alt=\"gel\" title=\"gel\" \/><span><span>Gel<\/span><\/span><\/span> <span class=\"note-text\">(20)<\/span><\/li><li><span class=\"i\"><img src=\".\/data\/images\/platinum crown.png\" alt=\"platinum crown\" title=\"platinum crown\" \/><span><span>Platinum Crown<\/span><\/span><\/span><\/li><\/ul><\/td><\/tr><tr data-rowid=\"10\"><td class=\"result\" rowspan=\"2\"><span class=\"i multi-line\"><img src=\".\/data\/images\/slime crown.png\" alt=\"slime crown\" title=\"slime crown\" \/><span><span>Slime Crown<\/span><\/span><\/span> (<img src=\".\/data\/images\/old-gen console version.png\" alt=\"old-gen console version\" title=\"old-gen console version\" \/>\u2009<img src=\".\/data\/images\/3ds version.png\" alt=\"3ds version\" title=\"3ds version\" \/>)<\/td><td class=\"ingredients\"><ul><li><span class=\"i\"><img src=\".\/data\/images\/gel.png\" alt=\"gel\" title=\"gel\" \/><span><span>Gel<\/span><\/span><\/span> <span class=\"note-text\">(99)<\/span><\/li><li><span class=\"i\"><img src=\".\/data\/images\/gold crown.png\" alt=\"gold crown\" title=\"gold crown\" \/><span><span>Gold Crown<\/span><\/span><\/span><\/li><\/ul><\/td><\/tr><tr data-rowid=\"11\"><td class=\"ingredients\"><ul><li><span class=\"i\"><img src=\".\/data\/images\/gel.png\" alt=\"gel\" title=\"gel\" \/><span><span>Gel<\/span><\/span><\/span> <span class=\"note-text\">(99)<\/span><\/li><li><span class=\"i\"><img src=\".\/data\/images\/platinum crown.png\" alt=\"platinum crown\" title=\"platinum crown\" \/><span><span>Platinum Crown<\/span><\/span><\/span><\/li><\/ul><\/td><\/tr><tr data-rowid=\"12\"><td class=\"result\" rowspan=\"1\"><span class=\"i multi-line\"><img src=\".\/data\/images\/lesser healing potion.png\" alt=\"lesser healing potion\" title=\"lesser healing potion\" \/><span><span>Lesser Healing Potion<\/span><\/span><\/span> <span class=\"note-text\">(2)<\/span><\/td><td class=\"ingredients\"><ul><li><span class=\"i\"><img src=\".\/data\/images\/mushroom.png\" alt=\"mushroom\" title=\"mushroom\" \/><span><span>Mushroom<\/span><\/span><\/span><\/li><li><span class=\"i\"><img src=\".\/data\/images\/gel.png\" alt=\"gel\" title=\"gel\" \/><span><span>Gel<\/span><\/span><\/span> <span class=\"note-text\">(2)<\/span><\/li><li><span class=\"i\"><img src=\".\/data\/images\/bottle.png\" alt=\"bottle\" title=\"bottle\" \/><span><span>Bottle<\/span><\/span><\/span> <span class=\"note-text\">(2)<\/span><\/li><\/ul><\/td><td class=\"station\" rowspan=\"1\"><span class=\"i\"><img src=\".\/data\/images\/placed bottle.png\" alt=\"placed bottle\" title=\"placed bottle\" \/><span><span>Placed Bottle<\/span><\/span><\/span><br><i><b>or<\/b><\/i><br><span class=\"i -w\"><img src=\".\/data\/images\/alchemy table.png\" alt=\"alchemy table\" title=\"alchemy table\" \/><span><span>Alchemy Table<\/span><span class=\"eico\"><img src=\".\/data\/images\/desktop, console, and mobile versions.png\" alt=\"desktop, console, and mobile versions\" title=\"desktop, console, and mobile versions\" \/><\/span><\/span><\/span><\/td><\/tr><tr data-rowid=\"13\"><td class=\"result\" rowspan=\"1\"><span class=\"i multi-line\"><img src=\".\/data\/images\/slime block.png\" alt=\"slime block\" title=\"slime block\" \/><span><span>Slime Block<\/span><\/span><\/span><\/td><td class=\"ingredients\"><ul><li><span class=\"i\"><img src=\".\/data\/images\/gel.png\" alt=\"gel\" title=\"gel\" \/><span><span>Gel<\/span><\/span><\/span><\/li><\/ul><\/td><td class=\"station\" rowspan=\"1\"><span class=\"i\"><img src=\".\/data\/images\/solidifier.png\" alt=\"solidifier\" title=\"solidifier\" \/><span><span>Solidifier<\/span><\/span><\/span><\/td><\/tr><\/tbody><\/table><div style=\"display: none\">total: 13 row(s)<\/div><\/div><\/div>"
        }
    ]
}