{
    "link": "https:\/\/terraria.gamepedia.com\/Imbuing_Station",
    "title": "Imbuing Station",
    "info": "The <b>Imbuing Station<\/b> is a crafting station used to craft Flasks. Flasks temporarily \"imbue\" melee weapons and whips with the ability to inflict a bonus debuff on enemies (with the exception of the Flask of Party, which only causes visual effects). Only one Flask can be in effect at any given time, and using another will cancel the last. Weapon imbuements last after death. Flasks affect all weapons that inflict melee damage, including Boomerangs and projectile melee weapons, as well as Whips. The Imbuing Station is purchased from the Witch Doctor for <span class=\"coin\" title=\"7 Gold Coins\" data-sort-value=\"70000\"><span class=\"gc\">7<\/span><\/span>.\n",
    "stat": {
        "image": "<div class=\"section images\"><ul class=\"infobox-inline\"><li><img src=\".\/data\/images\/imbuing station.png\" alt=\"imbuing station\" title=\"imbuing station\" \/><\/li><li><img src=\".\/data\/images\/imbuing station placed.png\" alt=\"imbuing station placed\" title=\"imbuing station placed\" \/><\/li><\/ul><div class=\"auto\"><img src=\".\/data\/images\/auto-use.png\" alt=\"auto-use\" title=\"auto-use\" \/><\/div><div class=\"stack\" title=\"Max stack: 99\"><span style=\"cursor:pointer\"><img src=\".\/data\/images\/stack digit 9.png\" alt=\"stack digit 9\" title=\"stack digit 9\" \/><img src=\".\/data\/images\/stack digit 9.png\" alt=\"stack digit 9\" title=\"stack digit 9\" \/><\/span><\/div><\/div>",
        "table": "<table class=\"stat\"><tbody><tr><th>Type<\/th><td><div class=\"tags\"><span class=\"nowrap tag\">Furniture<\/span><span class=\"nowrap tag\">Crafting station<\/span><\/div><\/td><\/tr><tr><th>Placeable<\/th><td><img src=\".\/data\/images\/yes.png\" alt=\"yes\" title=\"yes\" \/> <span class=\"small-bold\">(3 wide\u00a0\u00d7\u00a03 high)<\/span><\/td><\/tr><tr><th>Use time<\/th><td>15 <span class=\"usetime\">(Very fast)<\/span><\/td><\/tr><tr><th>Tooltip<\/th><td><i>Used to craft weapon imbuement flasks<\/i><\/td><\/tr><tr><th>Rarity<\/th><td><span class=\"rarity\"><s style=\"display:none;\">02*<\/s><img src=\".\/data\/images\/rarity level: 2.png\" alt=\"rarity level: 2\" title=\"rarity level: 2\" \/><\/span><\/td><\/tr><tr><th>Buy<\/th><td><span class=\"coin\" title=\"7 Gold Coins\" data-sort-value=\"70000\"><span class=\"gc\">7<\/span><\/span><\/td><\/tr><tr><th>Sell<\/th><td><span class=\"coin\" title=\"1 Gold 40 Silver Coins\" data-sort-value=\"14000\"><span class=\"gc\">1<\/span><span class=\"sc\">40<\/span><\/span><\/td><\/tr><tr><th>Research<\/th><td><abbr style=\"color:#C70A7D;font-weight:bold;\" title=\"Journey Mode\">1 required<\/abbr><\/td><\/tr><\/tbody><\/table>"
    },
    "craft": [
        {
            "title": "Imbuing Station",
            "info": "",
            "table": "<div class=\"crafts\"><div class=\"wrap\"><table class=\"sortable\" cellpadding=\"0\" cellspacing=\"0\"><caption><span class=\"i\"><img src=\".\/data\/images\/imbuing station.png\" alt=\"imbuing station\" title=\"imbuing station\" \/><span><span>Imbuing Station<\/span><\/span><\/span><\/caption><tbody><tr><th class=\"result\">Result<\/th><th class=\"ingredients\">Ingredients<\/th><\/tr><tr data-rowid=\"1\"><td class=\"result\" rowspan=\"1\"><span class=\"i multi-line\"><img src=\".\/data\/images\/flask of cursed flames.png\" alt=\"flask of cursed flames\" title=\"flask of cursed flames\" \/><span><span>Flask of Cursed Flames<\/span><\/span><\/span> (<img src=\".\/data\/images\/desktop version.png\" alt=\"desktop version\" title=\"desktop version\" \/>\u2009<img src=\".\/data\/images\/console version.png\" alt=\"console version\" title=\"console version\" \/>\u2009<img src=\".\/data\/images\/mobile version.png\" alt=\"mobile version\" title=\"mobile version\" \/>)<\/td><td class=\"ingredients\"><ul><li><span class=\"i\"><img src=\".\/data\/images\/bottled water.png\" alt=\"bottled water\" title=\"bottled water\" \/><span><span>Bottled Water<\/span><\/span><\/span><\/li><li><span class=\"i\"><img src=\".\/data\/images\/cursed flame.png\" alt=\"cursed flame\" title=\"cursed flame\" \/><span><span>Cursed Flame<\/span><\/span><\/span> <span class=\"note-text\">(2)<\/span><\/li><\/ul><\/td><\/tr><tr data-rowid=\"2\"><td class=\"result\" rowspan=\"1\"><span class=\"i multi-line\"><img src=\".\/data\/images\/flask of cursed flames.png\" alt=\"flask of cursed flames\" title=\"flask of cursed flames\" \/><span><span>Flask of Cursed Flames<\/span><\/span><\/span> (<img src=\".\/data\/images\/old-gen console version.png\" alt=\"old-gen console version\" title=\"old-gen console version\" \/>\u2009<img src=\".\/data\/images\/3ds version.png\" alt=\"3ds version\" title=\"3ds version\" \/>)<\/td><td class=\"ingredients\"><ul><li><span class=\"i\"><img src=\".\/data\/images\/bottled water.png\" alt=\"bottled water\" title=\"bottled water\" \/><span><span>Bottled Water<\/span><\/span><\/span><\/li><li><span class=\"i\"><img src=\".\/data\/images\/cursed flame.png\" alt=\"cursed flame\" title=\"cursed flame\" \/><span><span>Cursed Flame<\/span><\/span><\/span> <span class=\"note-text\">(5)<\/span><\/li><\/ul><\/td><\/tr><tr data-rowid=\"3\"><td class=\"result\" rowspan=\"1\"><span class=\"i multi-line\"><img src=\".\/data\/images\/flask of fire.png\" alt=\"flask of fire\" title=\"flask of fire\" \/><span><span>Flask of Fire<\/span><\/span><\/span> (<img src=\".\/data\/images\/desktop version.png\" alt=\"desktop version\" title=\"desktop version\" \/>\u2009<img src=\".\/data\/images\/console version.png\" alt=\"console version\" title=\"console version\" \/>\u2009<img src=\".\/data\/images\/mobile version.png\" alt=\"mobile version\" title=\"mobile version\" \/>)<\/td><td class=\"ingredients\"><ul><li><span class=\"i\"><img src=\".\/data\/images\/bottled water.png\" alt=\"bottled water\" title=\"bottled water\" \/><span><span>Bottled Water<\/span><\/span><\/span><\/li><li><span class=\"i\"><img src=\".\/data\/images\/hellstone.png\" alt=\"hellstone\" title=\"hellstone\" \/><span><span>Hellstone<\/span><\/span><\/span> <span class=\"note-text\">(3)<\/span><\/li><\/ul><\/td><\/tr><tr data-rowid=\"4\"><td class=\"result\" rowspan=\"1\"><span class=\"i multi-line\"><img src=\".\/data\/images\/flask of fire.png\" alt=\"flask of fire\" title=\"flask of fire\" \/><span><span>Flask of Fire<\/span><\/span><\/span> (<img src=\".\/data\/images\/old-gen console version.png\" alt=\"old-gen console version\" title=\"old-gen console version\" \/>\u2009<img src=\".\/data\/images\/3ds version.png\" alt=\"3ds version\" title=\"3ds version\" \/>)<\/td><td class=\"ingredients\"><ul><li><span class=\"i\"><img src=\".\/data\/images\/bottled water.png\" alt=\"bottled water\" title=\"bottled water\" \/><span><span>Bottled Water<\/span><\/span><\/span><\/li><li><span class=\"i\"><img src=\".\/data\/images\/hellstone.png\" alt=\"hellstone\" title=\"hellstone\" \/><span><span>Hellstone<\/span><\/span><\/span> <span class=\"note-text\">(5)<\/span><\/li><\/ul><\/td><\/tr><tr data-rowid=\"5\"><td class=\"result\" rowspan=\"1\"><span class=\"i multi-line\"><img src=\".\/data\/images\/flask of gold.png\" alt=\"flask of gold\" title=\"flask of gold\" \/><span><span>Flask of Gold<\/span><\/span><\/span><\/td><td class=\"ingredients\"><ul><li><span class=\"i\"><img src=\".\/data\/images\/bottled water.png\" alt=\"bottled water\" title=\"bottled water\" \/><span><span>Bottled Water<\/span><\/span><\/span><\/li><li><span class=\"i\"><img src=\".\/data\/images\/gold dust.png\" alt=\"gold dust\" title=\"gold dust\" \/><span><span>Gold Dust<\/span><\/span><\/span> <span class=\"note-text\">(5)<\/span><\/li><\/ul><\/td><\/tr><tr data-rowid=\"6\"><td class=\"result\" rowspan=\"1\"><span class=\"i multi-line\"><img src=\".\/data\/images\/flask of ichor.png\" alt=\"flask of ichor\" title=\"flask of ichor\" \/><span><span>Flask of Ichor<\/span><\/span><\/span> (<img src=\".\/data\/images\/desktop version.png\" alt=\"desktop version\" title=\"desktop version\" \/>\u2009<img src=\".\/data\/images\/console version.png\" alt=\"console version\" title=\"console version\" \/>\u2009<img src=\".\/data\/images\/mobile version.png\" alt=\"mobile version\" title=\"mobile version\" \/>)<\/td><td class=\"ingredients\"><ul><li><span class=\"i\"><img src=\".\/data\/images\/bottled water.png\" alt=\"bottled water\" title=\"bottled water\" \/><span><span>Bottled Water<\/span><\/span><\/span><\/li><li><span class=\"i\"><img src=\".\/data\/images\/ichor.png\" alt=\"ichor\" title=\"ichor\" \/><span><span>Ichor<\/span><\/span><\/span> <span class=\"note-text\">(2)<\/span><\/li><\/ul><\/td><\/tr><tr data-rowid=\"7\"><td class=\"result\" rowspan=\"1\"><span class=\"i multi-line\"><img src=\".\/data\/images\/flask of ichor.png\" alt=\"flask of ichor\" title=\"flask of ichor\" \/><span><span>Flask of Ichor<\/span><\/span><\/span> (<img src=\".\/data\/images\/old-gen console version.png\" alt=\"old-gen console version\" title=\"old-gen console version\" \/>\u2009<img src=\".\/data\/images\/3ds version.png\" alt=\"3ds version\" title=\"3ds version\" \/>)<\/td><td class=\"ingredients\"><ul><li><span class=\"i\"><img src=\".\/data\/images\/bottled water.png\" alt=\"bottled water\" title=\"bottled water\" \/><span><span>Bottled Water<\/span><\/span><\/span><\/li><li><span class=\"i\"><img src=\".\/data\/images\/ichor.png\" alt=\"ichor\" title=\"ichor\" \/><span><span>Ichor<\/span><\/span><\/span> <span class=\"note-text\">(5)<\/span><\/li><\/ul><\/td><\/tr><tr data-rowid=\"8\"><td class=\"result\" rowspan=\"1\"><span class=\"i multi-line\"><img src=\".\/data\/images\/flask of nanites.png\" alt=\"flask of nanites\" title=\"flask of nanites\" \/><span><span>Flask of Nanites<\/span><\/span><\/span><\/td><td class=\"ingredients\"><ul><li><span class=\"i\"><img src=\".\/data\/images\/bottled water.png\" alt=\"bottled water\" title=\"bottled water\" \/><span><span>Bottled Water<\/span><\/span><\/span><\/li><li><span class=\"i\"><img src=\".\/data\/images\/nanites.png\" alt=\"nanites\" title=\"nanites\" \/><span><span>Nanites<\/span><\/span><\/span> <span class=\"note-text\">(5)<\/span><\/li><\/ul><\/td><\/tr><tr data-rowid=\"9\"><td class=\"result\" rowspan=\"1\"><span class=\"i multi-line\"><img src=\".\/data\/images\/flask of party.png\" alt=\"flask of party\" title=\"flask of party\" \/><span><span>Flask of Party<\/span><\/span><\/span><\/td><td class=\"ingredients\"><ul><li><span class=\"i\"><img src=\".\/data\/images\/bottled water.png\" alt=\"bottled water\" title=\"bottled water\" \/><span><span>Bottled Water<\/span><\/span><\/span><\/li><li><span class=\"i\"><img src=\".\/data\/images\/confetti.png\" alt=\"confetti\" title=\"confetti\" \/><span><span>Confetti<\/span><\/span><\/span> <span class=\"note-text\">(5)<\/span><\/li><\/ul><\/td><\/tr><tr data-rowid=\"10\"><td class=\"result\" rowspan=\"1\"><span class=\"i multi-line\"><img src=\".\/data\/images\/flask of poison.png\" alt=\"flask of poison\" title=\"flask of poison\" \/><span><span>Flask of Poison<\/span><\/span><\/span> (<img src=\".\/data\/images\/desktop version.png\" alt=\"desktop version\" title=\"desktop version\" \/>\u2009<img src=\".\/data\/images\/console version.png\" alt=\"console version\" title=\"console version\" \/>\u2009<img src=\".\/data\/images\/mobile version.png\" alt=\"mobile version\" title=\"mobile version\" \/>)<\/td><td class=\"ingredients\"><ul><li><span class=\"i\"><img src=\".\/data\/images\/bottled water.png\" alt=\"bottled water\" title=\"bottled water\" \/><span><span>Bottled Water<\/span><\/span><\/span><\/li><li><span class=\"i\"><img src=\".\/data\/images\/stinger.png\" alt=\"stinger\" title=\"stinger\" \/><span><span>Stinger<\/span><\/span><\/span><\/li><\/ul><\/td><\/tr><tr data-rowid=\"11\"><td class=\"result\" rowspan=\"1\"><span class=\"i multi-line\"><img src=\".\/data\/images\/flask of poison.png\" alt=\"flask of poison\" title=\"flask of poison\" \/><span><span>Flask of Poison<\/span><\/span><\/span> (<img src=\".\/data\/images\/old-gen console version.png\" alt=\"old-gen console version\" title=\"old-gen console version\" \/>\u2009<img src=\".\/data\/images\/3ds version.png\" alt=\"3ds version\" title=\"3ds version\" \/>)<\/td><td class=\"ingredients\"><ul><li><span class=\"i\"><img src=\".\/data\/images\/bottled water.png\" alt=\"bottled water\" title=\"bottled water\" \/><span><span>Bottled Water<\/span><\/span><\/span><\/li><li><span class=\"i\"><img src=\".\/data\/images\/stinger.png\" alt=\"stinger\" title=\"stinger\" \/><span><span>Stinger<\/span><\/span><\/span> <span class=\"note-text\">(5)<\/span><\/li><\/ul><\/td><\/tr><tr data-rowid=\"12\"><td class=\"result\" rowspan=\"1\"><span class=\"i multi-line\"><img src=\".\/data\/images\/flask of venom.png\" alt=\"flask of venom\" title=\"flask of venom\" \/><span><span>Flask of Venom<\/span><\/span><\/span><\/td><td class=\"ingredients\"><ul><li><span class=\"i\"><img src=\".\/data\/images\/bottled water.png\" alt=\"bottled water\" title=\"bottled water\" \/><span><span>Bottled Water<\/span><\/span><\/span><\/li><li><span class=\"i\"><img src=\".\/data\/images\/vial of venom.png\" alt=\"vial of venom\" title=\"vial of venom\" \/><span><span>Vial of Venom<\/span><\/span><\/span> <span class=\"note-text\">(5)<\/span><\/li><\/ul><\/td><\/tr><\/tbody><\/table><div style=\"display: none\">total: 12 row(s)<\/div><\/div><\/div>"
        }
    ]
}