{
    "link": "https:\/\/terraria.gamepedia.com\/Jack_'O_Lantern_Mask",
    "title": "Jack 'O Lantern Mask",
    "info": "The <b>Jack 'O Lantern Mask<\/b> is a vanity item uncommonly dropped by Headless Horsemen. The inventory icon shows it as unlit, but upon placing it in the armor slot, it is rendered with a glowing pattern over the face. This is visible even if in darkness or stealth from Shroomite\/Vortex armor\/Psycho Knife. When displayed on a Mannequin, it is shown without the glow. Additionally, using dyes on the mask will change the color of the pumpkin, while leaving the glow unaffected, which may be unintentional.\n",
    "stat": "<table class=\"stat\"><tbody><tr><th>Type<\/th><td><div class=\"tags\"><span class=\"nowrap tag\">Vanity<\/span><\/div><\/td><\/tr><tr><th>Body slot<\/th><td>Social Helmet<\/td><\/tr><tr><th>Rarity<\/th><td><span class=\"rarity\"><s style=\"display:none;\">03*<\/s><img src=\".\/data\/images\/rarity level: 3.png\" alt=\"rarity level: 3\" title=\"rarity level: 3\" \/><\/span><\/td><\/tr><tr><th>Sell<\/th><td><span class=\"coin\" title=\"5 Gold Coins\" data-sort-value=\"50000\"><span class=\"gc\">5<\/span><\/span><\/td><\/tr><tr><th>Research<\/th><td><abbr style=\"color:#C70A7D;font-weight:bold;\" title=\"Journey Mode\">1 required<\/abbr><\/td><\/tr><\/tbody><\/table>",
    "craft": []
}