{
    "link": "https:\/\/terraria.gamepedia.com\/Rod_of_Discord",
    "title": "Rod of Discord",
    "info": "The <b>Rod of Discord<\/b> is a Hardmode tool that instantly teleports the player to the mouse cursor. It has a 0.2% \/ <span class=\"eico\"><img src=\".\/data\/images\/desktop and mobile versions.png\" alt=\"desktop and mobile versions\" title=\"desktop and mobile versions\" \/><\/span> <abbr class=\"expert\" title=\"Expert Mode\">0.25%<\/abbr> (1\/500 \/ <span class=\"eico\"><img src=\".\/data\/images\/desktop and mobile versions.png\" alt=\"desktop and mobile versions\" title=\"desktop and mobile versions\" \/><\/span> <abbr class=\"expert\" title=\"Expert Mode\">1\/400<\/abbr>) chance of being dropped by Chaos Elementals.\n",
    "stat": "<table class=\"stat\"><tbody><tr><th>Type<\/th><td><div class=\"tags\"><span class=\"nowrap tag\">Tool<\/span><\/div><\/td><\/tr><tr><th>Use time<\/th><td>20 <span class=\"usetime\">(Very fast)<\/span><\/td><\/tr><tr><th>Tooltip<\/th><td><i>Teleports you to the position of the mouse<br><img src=\".\/data\/images\/mobile version.png\" alt=\"mobile version\" title=\"mobile version\" \/> Teleports you to the position of the cursor<\/i><\/td><\/tr><tr><th>Rarity<\/th><td><span class=\"rarity\"><s style=\"display:none;\">07*<\/s><img src=\".\/data\/images\/rarity level: 7.png\" alt=\"rarity level: 7\" title=\"rarity level: 7\" \/><\/span><\/td><\/tr><tr><th>Sell<\/th><td><span class=\"coin\" title=\"10 Gold Coins\" data-sort-value=\"100000\"><span class=\"gc\">10<\/span><\/span><\/td><\/tr><tr><th>Research<\/th><td><abbr style=\"color:#C70A7D;font-weight:bold;\" title=\"Journey Mode\">1 required<\/abbr><\/td><\/tr><\/tbody><\/table>",
    "craft": []
}