{
    "link": "https:\/\/terraria.gamepedia.com\/The_Eye_of_Cthulhu",
    "title": "The Eye of Cthulhu",
    "info": "<b>The Eye of Cthulhu<\/b> is a Hardmode, post-Plantera Yoyo which has a 33.33% \/ <abbr class=\"expert\" title=\"Expert Mode\">55.56%<\/abbr> chance to drop from Mothron during a Solar Eclipse. It is one of the few yoyos that can stay in the air indefinitely, and it has a reach of 23 tiles. It is currently the second strongest yoyo in the game, only beaten by the Terrarian.\n",
    "stat": "<table class=\"stat\"><tbody><tr><th>Type<\/th><td><div class=\"tags\"><span class=\"nowrap tag\">Weapon<\/span><\/div><\/td><\/tr><tr><th>Damage<\/th><td>115 <span class=\"small-bold\">(Melee)<\/span><\/td><\/tr><tr><th>Knockback<\/th><td>3.5 <span class=\"knockback\">(Weak)<\/span><\/td><\/tr><tr><th>Critical chance<\/th><td>4%<\/td><\/tr><tr><th>Use time<\/th><td>25 <span class=\"usetime\">(Fast)<\/span><\/td><\/tr><tr><th>Velocity<\/th><td>16<\/td><\/tr><tr><th>Rarity<\/th><td><span class=\"rarity\"><s style=\"display:none;\">08*<\/s><img src=\".\/data\/images\/rarity level: 8.png\" alt=\"rarity level: 8\" title=\"rarity level: 8\" \/><\/span><\/td><\/tr><tr><th>Sell<\/th><td><span class=\"coin\" title=\"12 Gold 50 Silver Coins\" data-sort-value=\"125000\"><span class=\"gc\">12<\/span><span class=\"sc\">50<\/span><\/span><\/td><\/tr><tr><th>Research<\/th><td><abbr style=\"color:#C70A7D;font-weight:bold;\" title=\"Journey Mode\">1 required<\/abbr><\/td><\/tr><\/tbody><\/table>",
    "craft": []
}